{
    "id": "anime-notes",
    "name": "Anime Notes",
    "version": "1.0.0",
    "manifestURI": "https://raw.githubusercontent.com/faddix/anime-notes/main/anime-notes.json",
    "language": "typescript",
    "type": "plugin",
    "description": "✏️ Add personal notes to anime",
    "author": "Faddix",
    "icon": "https://raw.githubusercontent.com/faddix/anime-notes/main/src/notepad.png",
    "website": "",
    "lang": "en",
    "payloadURI": "https://raw.githubusercontent.com/faddix/anime-notes/main/AnimeNotes.ts",
    "plugin": {
        "version": "1",
        "permissions": {
            "scopes": ["storage"]
        }
    },
    "isDevelopment": false
}
